minim/__init__.py
minim/audio.py
minim/discogs.py
minim/itunes.py
minim/qobuz.py
minim/spotify.py
minim/tidal.py
minim/utility.py
minim-1.0.0.dist-info/LICENSE
minim-1.0.0.dist-info/METADATA
minim-1.0.0.dist-info/WHEEL
minim-1.0.0.dist-info/top_level.txt
minim-1.0.0.dist-info/RECORD
