Metadata-Version: 2.1
Name: minim
Version: 1.0.0
Summary: A collection of music service APIs to query media information and 
Author-email: Benjamin Ye <benjaminbobinye@gmail.com>
Project-URL: Homepage, https://github.com/bbye98/minim
Project-URL: Bug Tracker, https://github.com/bbye98/minim/issues
Classifier: Operating System :: OS Independent
Classifier: Programming Language :: Python
Classifier: Programming Language :: Python :: 3
Requires-Python: >=3.9
License-File: LICENSE
Requires-Dist: cryptography
Requires-Dist: mutagen
Requires-Dist: requests
